sc_inetbox_adapter/__init__.py
sc_inetbox_adapter/const.py
sc_inetbox_adapter/errors.py
sc_inetbox_adapter/sc_inetbox_adapter.py
sc_inetbox_adapter-0.1.2.dist-info/LICENSE
sc_inetbox_adapter-0.1.2.dist-info/METADATA
sc_inetbox_adapter-0.1.2.dist-info/WHEEL
sc_inetbox_adapter-0.1.2.dist-info/RECORD
