Metadata-Version: 2.1
Name: sc-inetbox-adapter
Version: 0.1.2
Summary: API adapter for Swisscom Internet Box
License: GNU General Public License v3.0
Author: Matthias Weis
Requires-Python: >=3.8,<4.0
Classifier: License :: Other/Proprietary License
Classifier: Programming Language :: Python :: 3
Classifier: Programming Language :: Python :: 3.8
Classifier: Programming Language :: Python :: 3.9
Classifier: Programming Language :: Python :: 3.10
Classifier: Programming Language :: Python :: 3.11
Requires-Dist: requests (>=2.28.2,<3.0.0)
